LICENCE
README.md
setup.py
lealNumeros/__init__.py
lealNumeros/main.py
lealnumeros.egg-info/PKG-INFO
lealnumeros.egg-info/SOURCES.txt
lealnumeros.egg-info/dependency_links.txt
lealnumeros.egg-info/requires.txt
lealnumeros.egg-info/top_level.txt