Metadata-Version: 2.1
Name: lealnumeros
Version: 0.0.5
Summary: Trabalhe com formatação de números de uma maneira rápido e fácil.
Author: José Rodolfo
Author-email: silvaleal.ctt@gmail.com
License: MIT License
Keywords: lealnumeros
License-File: LICENCE
